odoo/addons/record_archiver/README.rst
odoo/addons/record_archiver/__init__.py
odoo/addons/record_archiver/__manifest__.py
odoo/addons/record_archiver/data/cron.xml
odoo/addons/record_archiver/i18n/record_archiver.pot
odoo/addons/record_archiver/models/__init__.py
odoo/addons/record_archiver/models/ir_model.py
odoo/addons/record_archiver/models/record_lifespan.py
odoo/addons/record_archiver/readme/CONFIGURE.rst
odoo/addons/record_archiver/readme/CONTRIBUTORS.rst
odoo/addons/record_archiver/readme/DESCRIPTION.rst
odoo/addons/record_archiver/readme/ROADMAP.rst
odoo/addons/record_archiver/readme/USAGE.rst
odoo/addons/record_archiver/security/ir.model.access.csv
odoo/addons/record_archiver/static/description/icon.png
odoo/addons/record_archiver/static/description/index.html
odoo/addons/record_archiver/tests/__init__.py
odoo/addons/record_archiver/tests/test_active_search.py
odoo/addons/record_archiver/tests/test_archive.py
odoo/addons/record_archiver/views/record_lifespan_view.xml
odoo11_addon_record_archiver-11.0.1.0.0.99.dev6.dist-info/METADATA
odoo11_addon_record_archiver-11.0.1.0.0.99.dev6.dist-info/WHEEL
odoo11_addon_record_archiver-11.0.1.0.0.99.dev6.dist-info/top_level.txt
odoo11_addon_record_archiver-11.0.1.0.0.99.dev6.dist-info/RECORD
